bytedvrtvrouter/__init__.py
bytedvrtvrouter-0.0.1.dist-info/METADATA
bytedvrtvrouter-0.0.1.dist-info/WHEEL
bytedvrtvrouter-0.0.1.dist-info/top_level.txt
bytedvrtvrouter-0.0.1.dist-info/RECORD
